<?xml version="1.0" encoding="UTF-8" ?><tv>
<channel id="WMNSLP.us"><display-name>CBS (WMNS-LP) Charlotte/Amalie, VI</display-name><icon src="https://cdn.tvpassport.com/image/station/100x100/cbs.png"/><url>https://tvtv.us</url></channel>
<channel id="WVGNLD.us"><display-name>NBC (WVGN) Charlotte Amalie, VI</display-name><icon src="https://cdn.tvpassport.com/image/station/100x100/nbc.png"/><url>https://tvtv.us</url></channel>
<channel id="WVXF.us"><display-name>THIS (WVXF) Saint Thomas, VI</display-name><icon src="https://cdn.tvpassport.com/image/station/100x100/this_tv.png"/><url>https://tvtv.us</url></channel>
<programme start="20211118210000 +0000" stop="20211119010000 +0000" channel="WMNSLP.us"><title lang="en">Local Programming</title><desc lang="en">Local programming.</desc><category lang="en">Local</category></programme>
<programme start="20211119010000 +0000" stop="20211119013100 +0000" channel="WMNSLP.us"><title lang="en">Young Sheldon</title><desc lang="en">Sheldon takes his first engineering class with Professor Boucher.</desc><category lang="en">Sitcom</category><icon src="https://cdn.tvpassport.com/image/show/480x720/72632.jpg"/></programme>
<programme start="20211119013100 +0000" stop="20211119020100 +0000" channel="WMNSLP.us"><title lang="en">United States of Al</title><desc lang="en">When Al struggles with the college class he is taking, Riley takes it upon himself to speak to his professor.</desc><category lang="en">Sitcom</category><icon src="https://cdn.tvpassport.com/image/show/480x720/107091.jpg"/></programme>
<programme start="20211119020100 +0000" stop="20211119023000 +0000" channel="WMNSLP.us"><title lang="en">Ghosts</title><desc lang="en">After Jay is kicked out of a Dungeons &amp; Dragons campaign with his city friends, Sam agrees to facilitate a new one between him and the ghosts.</desc><category lang="en">Sitcom</category><icon src="https://cdn.tvpassport.com/image/show/480x720/115876.jpg"/></programme>
<programme start="20211119023000 +0000" stop="20211119030000 +0000" channel="WMNSLP.us"><title lang="en">B Positive</title><desc lang="en">Gina is pressured by the seniors at Valley Hills to fire the chef.</desc><category lang="en">Sitcom</category><icon src="https://cdn.tvpassport.com/image/show/480x720/99443.jpg"/></programme>
<programme start="20211119030000 +0000" stop="20211119040000 +0000" channel="WMNSLP.us"><title lang="en">Bull</title><desc lang="en">Bull and Chunk represent an emergency room doctor being sued for malpractice after she ignored direct orders to save one near-death patient in favor of helping another who was also critically injured.</desc><category lang="en">Drama</category><icon src="https://cdn.tvpassport.com/image/show/480x720/63780.jpg"/></programme>
<programme start="20211119040000 +0000" stop="20211119043500 +0000" channel="WMNSLP.us"><title lang="en">Local Programming</title><desc lang="en">Local programming.</desc><category lang="en">Local</category></programme>
<programme start="20211119043500 +0000" stop="20211119053700 +0000" channel="WMNSLP.us"><title lang="en">The Late Show With Stephen Colbert</title><desc lang="en">Bruce Springsteen is interviewed and performs.</desc><category lang="en">Talk Shows</category><icon src="https://cdn.tvpassport.com/image/show/480x720/33468.jpg"/></programme>
<programme start="20211119053700 +0000" stop="20211119063700 +0000" channel="WMNSLP.us"><title lang="en">The Late Late Show With James Corden</title><desc lang="en">Salma Hayek and Keith Urban join James.</desc><category lang="en">Talk Shows</category><icon src="https://cdn.tvpassport.com/image/show/480x720/31174.jpg"/></programme>
<programme start="20211119063700 +0000" stop="20211119120000 +0000" channel="WMNSLP.us"><title lang="en">Local Programming</title><desc lang="en">Local programming.</desc><category lang="en">Local</category></programme>
<programme start="20211119120000 +0000" stop="20211119140000 +0000" channel="WMNSLP.us"><title lang="en">CBS Mornings</title><desc lang="en">Robert Plant and Alison Krauss visit.</desc><category lang="en">News</category></programme>
<programme start="20211119140000 +0000" stop="20211119160000 +0000" channel="WMNSLP.us"><title lang="en">Local Programming</title><desc lang="en">Local programming.</desc><category lang="en">Local</category></programme>
<programme start="20211119160000 +0000" stop="20211119170000 +0000" channel="WMNSLP.us"><title lang="en">The Price Is Right</title><desc lang="en">Contestants must correctly guess the retail price of various items in order to win cash and prizes.</desc><category lang="en">Game Shows</category><icon src="https://cdn.tvpassport.com/image/show/480x720/32042.jpg"/></programme>
<programme start="20211119170000 +0000" stop="20211119173000 +0000" channel="WMNSLP.us"><title lang="en">Local Programming</title><desc lang="en">Local programming.</desc><category lang="en">Local</category></programme>
<programme start="20211119173000 +0000" stop="20211119183000 +0000" channel="WMNSLP.us"><title lang="en">The Young and the Restless</title><desc lang="en">The rivalries, romances, hopes and fears of the residents of Genoa City.</desc><category lang="en">Soaps</category><icon src="https://cdn.tvpassport.com/image/show/480x720/13801.jpg"/></programme>
<programme start="20211119183000 +0000" stop="20211119190000 +0000" channel="WMNSLP.us"><title lang="en">The Bold and the Beautiful</title><desc lang="en">The Forrester and Spectra clans deal with relationships and the world of fashion.</desc><category lang="en">Soaps</category><icon src="https://cdn.tvpassport.com/image/show/480x720/1219.jpg"/></programme>
<programme start="20211119190000 +0000" stop="20211119200000 +0000" channel="WMNSLP.us"><title lang="en">The Talk</title><desc lang="en">Don Johnson and Cheech Marin visit.</desc><category lang="en">Talk Shows</category><icon src="https://cdn.tvpassport.com/image/show/480x720/32349.jpg"/></programme>
<programme start="20211119200000 +0000" stop="20211119210000 +0000" channel="WMNSLP.us"><title lang="en">Let&apos;s Make a Deal</title><desc lang="en">Audience members dressed in outlandish costumes try to win cash and prizes by making deals with the host.</desc><category lang="en">Game Shows</category></programme>
<programme start="20211119210000 +0000" stop="20211120010000 +0000" channel="WMNSLP.us"><title lang="en">Local Programming</title><desc lang="en">Local programming.</desc><category lang="en">Local</category></programme>
<programme start="20211119210000 +0000" stop="20211120010000 +0000" channel="WMNSLP.us"><title lang="en">Local Programming</title><desc lang="en">Local programming.</desc><category lang="en">Local</category></programme>
<programme start="20211120010000 +0000" stop="20211120020000 +0000" channel="WMNSLP.us"><title lang="en">S.W.A.T.</title><desc lang="en">The team works together to hunt down a deadly band of mercenaries hired by a wealthy CEO trying to leave the country before he’s arrested for running a massive Ponzi scheme.</desc><category lang="en">Drama</category><icon src="https://cdn.tvpassport.com/image/show/480x720/72758.jpg"/></programme>
<programme start="20211120020000 +0000" stop="20211120030000 +0000" channel="WMNSLP.us"><title lang="en">Magnum P.I.</title><desc lang="en">Kumu goes undercover in a retirement community when Higgins is hired to investigate the disappearance of a resident’s life savings.</desc><category lang="en">Drama</category><icon src="https://cdn.tvpassport.com/image/show/480x720/74811.jpg"/></programme>
<programme start="20211120030000 +0000" stop="20211120040000 +0000" channel="WMNSLP.us"><title lang="en">Blue Bloods</title><desc lang="en">Danny and Baez&apos;s attempts to find the culprit who assaulted a shop owner are hindered by the close-knit community’s refusal to cooperate with the investigation.</desc><category lang="en">Drama</category><icon src="https://cdn.tvpassport.com/image/show/480x720/11602.jpg"/></programme>
<programme start="20211120040000 +0000" stop="20211120043500 +0000" channel="WMNSLP.us"><title lang="en">Local Programming</title><desc lang="en">Local programming.</desc><category lang="en">Local</category></programme>
<programme start="20211120043500 +0000" stop="20211120053700 +0000" channel="WMNSLP.us"><title lang="en">The Late Show With Stephen Colbert</title><desc lang="en">Kevin Hart visits; Robert Plant and Alison Krauss perform.</desc><category lang="en">Talk Shows</category><icon src="https://cdn.tvpassport.com/image/show/480x720/33468.jpg"/></programme>
<programme start="20211120053700 +0000" stop="20211120063700 +0000" channel="WMNSLP.us"><title lang="en">The Late Late Show With James Corden</title><desc lang="en">Taraji P. Henson and Gabrielle Union visit; Jake Wesley Rogers performs.</desc><category lang="en">Talk Shows</category><icon src="https://cdn.tvpassport.com/image/show/480x720/31174.jpg"/></programme>
<programme start="20211120063700 +0000" stop="20211120110000 +0000" channel="WMNSLP.us"><title lang="en">Local Programming</title><desc lang="en">Local programming.</desc><category lang="en">Local</category></programme>
<programme start="20211120110000 +0000" stop="20211120130000 +0000" channel="WMNSLP.us"><title lang="en">CBS Saturday Morning</title><desc lang="en">Robert Plant and Alison Krauss perform.</desc><category lang="en">News Magazine</category></programme>
<programme start="20211120130000 +0000" stop="20211120170000 +0000" channel="WMNSLP.us"><title lang="en">Local Programming</title><desc lang="en">Local programming.</desc><category lang="en">Local</category></programme>
<programme start="20211120170000 +0000" stop="20211120193000 +0000" channel="WMNSLP.us"><title lang="en">Soccer</title><category lang="en">Sports, Soccer</category></programme>
<programme start="20211120193000 +0000" stop="20211120200000 +0000" channel="WMNSLP.us"><title lang="en">College Football: The Drive to Atlanta</title><desc lang="en">Adam Zucker, Rick Neuheisel and Brian Jones get you set for a ranked on ranked, SEC West showdown between Arkansas and Alabama.</desc><category lang="en">Sports, Football</category></programme>
<programme start="20211120200000 +0000" stop="20211120203000 +0000" channel="WMNSLP.us"><title lang="en">College Football Today</title><desc lang="en">Keeping viewers updated on all the games throughout the day with scores and highlights.</desc><category lang="en">Sports, Football</category><icon src="https://cdn.tvpassport.com/image/show/480x720/66839.jpg"/></programme>
<programme start="20211120203000 +0000" stop="20211121000000 +0000" channel="WMNSLP.us"><title lang="en">Football</title><desc lang="en">Football.</desc><category lang="en">Sports, Football</category></programme>
<programme start="20211119000000 +0000" stop="20211119010000 +0000" channel="WVGNLD.us"><title lang="en">The Kelly Clarkson Show</title><desc lang="en">Kelly Clarkson brings her voice to daytime TV, featuring feel-good stories and guests.</desc><category lang="en">Talk Shows</category><icon src="https://cdn.tvpassport.com/image/show/480x720/94470.jpg"/></programme>
<programme start="20211119010000 +0000" stop="20211119020000 +0000" channel="WVGNLD.us"><title lang="en">The Blacklist</title><desc lang="en">Dembe’s position as an FBI agent causes complications for Red as the Task Force handles a case involving military technology. Cooper and Park each find their personal lives increasingly complicated.</desc><category lang="en">Drama</category><icon src="https://cdn.tvpassport.com/image/show/480x720/10132.jpg"/></programme>
<programme start="20211119020000 +0000" stop="20211119030000 +0000" channel="WVGNLD.us"><title lang="en">Law &amp; Order: Special Victims Unit</title><desc lang="en">Benson and Rollins must contend with the FBI and the Organized Crime bureau when a rape victim identifies a dangerous mobster as her assailant.</desc><category lang="en">Drama</category><icon src="https://cdn.tvpassport.com/image/show/480x720/10771.jpg"/></programme>
<programme start="20211119030000 +0000" stop="20211119040000 +0000" channel="WVGNLD.us"><title lang="en">Law &amp; Order: Organized Crime</title><desc lang="en">After taking down Wheatley&apos;s drug empire and discovering his wife&apos;s killer, Det. Stabler must infiltrate a notorious crime family aiming to take over New York City’s cocaine trade.</desc><category lang="en">Drama</category><icon src="https://cdn.tvpassport.com/image/show/480x720/106782.jpg"/></programme>
<programme start="20211119040000 +0000" stop="20211119043500 +0000" channel="WVGNLD.us"><title lang="en">News for New York at 11:00 p.m.</title><category lang="en">News</category></programme>
<programme start="20211119043500 +0000" stop="20211119053500 +0000" channel="WVGNLD.us"><title lang="en">The Tonight Show Starring Jimmy Fallon</title><desc lang="en">Guests include Simu Liu, Ruth Negga and musical guest Big Sean and Hit-Boy.</desc><category lang="en">Talk Shows</category><icon src="https://cdn.tvpassport.com/image/show/480x720/13151.jpg"/></programme>
<programme start="20211119053500 +0000" stop="20211119063500 +0000" channel="WVGNLD.us"><title lang="en">Late Night With Seth Meyers</title><desc lang="en">Guests include Paul Rudd and Jared Harris. Nate Smith sits-in with the 8G Band.</desc><category lang="en">Talk Shows</category></programme>
<programme start="20211119063500 +0000" stop="20211119070000 +0000" channel="WVGNLD.us"><title lang="en">NBC Nightly News With Lester Holt</title><desc lang="en">This daily evening news program features the top national and international stories of the day.</desc><category lang="en">News</category><icon src="https://cdn.tvpassport.com/image/show/480x720/60238.jpg"/></programme>
<programme start="20211119070000 +0000" stop="20211119080000 +0000" channel="WVGNLD.us"><title lang="en">Today</title><desc lang="en">Features the latest in international news and weather, including newsmaker interviews.</desc><category lang="en">Talk Shows</category><icon src="https://cdn.tvpassport.com/image/show/480x720/33364.jpg"/></programme>
<programme start="20211119080000 +0000" stop="20211119083000 +0000" channel="WVGNLD.us"><title lang="en">Early Today</title><desc lang="en">A comprehensive look at overnight news, the day ahead, plus the latest weather from across the nation. Also featured are regular segments on business, sports and entertainment.</desc><category lang="en">News</category><icon src="https://cdn.tvpassport.com/image/show/480x720/51573.jpg"/></programme>
<programme start="20211119083000 +0000" stop="20211119090000 +0000" channel="WVGNLD.us"><title lang="en">Paid Program</title><desc lang="en">Paid programming.</desc><category lang="en">Paid Program</category></programme>
<programme start="20211119090000 +0000" stop="20211119093000 +0000" channel="WVGNLD.us"><title lang="en">Paid Program</title><desc lang="en">Paid programming.</desc><category lang="en">Paid Program</category></programme>
<programme start="20211119093000 +0000" stop="20211119100000 +0000" channel="WVGNLD.us"><title lang="en">Early Today</title><desc lang="en">A comprehensive look at overnight news, the day ahead, plus the latest weather from across the nation. Also featured are regular segments on business, sports and entertainment.</desc><category lang="en">News</category><icon src="https://cdn.tvpassport.com/image/show/480x720/51573.jpg"/></programme>
<programme start="20211119100000 +0000" stop="20211119103000 +0000" channel="WVGNLD.us"><title lang="en">Paid Program</title><desc lang="en">Paid programming.</desc><category lang="en">Paid Program</category></programme>
<programme start="20211119103000 +0000" stop="20211119110000 +0000" channel="WVGNLD.us"><title lang="en">Paid Program</title><desc lang="en">Paid programming.</desc><category lang="en">Paid Program</category></programme>
<programme start="20211119110000 +0000" stop="20211119120000 +0000" channel="WVGNLD.us"><title lang="en">Today in New York</title><desc lang="en">Breaking news, weather and traffic on the fours. Stay up to the minute, the minute you&apos;re up with News 4 New York.</desc><category lang="en">News</category></programme>
<programme start="20211119120000 +0000" stop="20211119140000 +0000" channel="WVGNLD.us"><title lang="en">Today</title><desc lang="en">Features the latest in international news and weather, including newsmaker interviews.</desc><category lang="en">Talk Shows</category><icon src="https://cdn.tvpassport.com/image/show/480x720/33364.jpg"/></programme>
<programme start="20211119140000 +0000" stop="20211119150000 +0000" channel="WVGNLD.us"><title lang="en">Today III</title><desc lang="en">Guests include Rosamund Pike and Jill Martin.</desc><category lang="en">Talk Shows</category><icon src="https://cdn.tvpassport.com/image/show/480x720/78953.jpg"/></programme>
<programme start="20211119150000 +0000" stop="20211119160000 +0000" channel="WVGNLD.us"><title lang="en">Today With Hoda and Jenna</title><desc lang="en">The hosts welcome Heather McMahan and Donal Skehan.</desc><category lang="en">Talk Shows</category><icon src="https://cdn.tvpassport.com/image/show/480x720/78952.jpg"/></programme>
<programme start="20211119160000 +0000" stop="20211119163000 +0000" channel="WVGNLD.us"><title lang="en">Business First AM</title><desc lang="en">An entertaining business news show giving everyday Americans an edge in the stock market straight from the trading floor.</desc><category lang="en">Business</category><icon src="https://cdn.tvpassport.com/image/show/480x720/103947.jpg"/></programme>
<programme start="20211119163000 +0000" stop="20211119170000 +0000" channel="WVGNLD.us"><title lang="en">Paid Program</title><desc lang="en">Paid programming.</desc><category lang="en">Paid Program</category></programme>
<programme start="20211119170000 +0000" stop="20211119173000 +0000" channel="WVGNLD.us"><title lang="en">Paid Program</title><desc lang="en">Paid programming.</desc><category lang="en">Paid Program</category></programme>
<programme start="20211119173000 +0000" stop="20211119180000 +0000" channel="WVGNLD.us"><title lang="en">Paid Program</title><desc lang="en">Paid programming.</desc><category lang="en">Paid Program</category></programme>
<programme start="20211119180000 +0000" stop="20211119190000 +0000" channel="WVGNLD.us"><title lang="en">Days of Our Lives</title><desc lang="en">The characters from Salem face challenges, day-to-day conflicts and supernatural forces.</desc><category lang="en">Soaps</category><icon src="https://cdn.tvpassport.com/image/show/480x720/1948.jpg"/></programme>
<programme start="20211119190000 +0000" stop="20211119193000 +0000" channel="WVGNLD.us"><title lang="en">Paid Program</title><desc lang="en">Paid programming.</desc><category lang="en">Paid Program</category></programme>
<programme start="20211119193000 +0000" stop="20211119200000 +0000" channel="WVGNLD.us"><title lang="en">Access Hollywood</title><desc lang="en">A daily look at the latest news and information from Hollywood and its celebrities.</desc><category lang="en">News Magazine</category><icon src="https://cdn.tvpassport.com/image/show/480x720/5926.jpg"/></programme>
<programme start="20211119200000 +0000" stop="20211119210000 +0000" channel="WVGNLD.us"><title lang="en">The Kelly Clarkson Show</title><desc lang="en">Kelly Clarkson brings her voice to daytime TV, featuring feel-good stories and guests.</desc><category lang="en">Talk Shows</category><icon src="https://cdn.tvpassport.com/image/show/480x720/94470.jpg"/></programme>
<programme start="20211119210000 +0000" stop="20211119220000 +0000" channel="WVGNLD.us"><title lang="en">Access Daily</title><desc lang="en">The latest celebrity news and opinions, as well as in-studio guests, fashion and more.</desc><category lang="en">News Magazine</category></programme>
<programme start="20211119220000 +0000" stop="20211119230000 +0000" channel="WVGNLD.us"><title lang="en">News for New York at 5:00 p.m.</title><category lang="en">News</category></programme>
<programme start="20211119230000 +0000" stop="20211119233000 +0000" channel="WVGNLD.us"><title lang="en">News for New York at 6:00 p.m.</title><category lang="en">News</category></programme>
<programme start="20211119233000 +0000" stop="20211120000000 +0000" channel="WVGNLD.us"><title lang="en">NBC Nightly News With Lester Holt</title><desc lang="en">This daily evening news program features the top national and international stories of the day.</desc><category lang="en">News</category><icon src="https://cdn.tvpassport.com/image/show/480x720/60238.jpg"/></programme>
<programme start="20211120000000 +0000" stop="20211120010000 +0000" channel="WVGNLD.us"><title lang="en">The Kelly Clarkson Show</title><desc lang="en">Kelly Clarkson brings her voice to daytime TV, featuring feel-good stories and guests.</desc><category lang="en">Talk Shows</category><icon src="https://cdn.tvpassport.com/image/show/480x720/94470.jpg"/></programme>
<programme start="20211120010000 +0000" stop="20211120020000 +0000" channel="WVGNLD.us"><title lang="en">The Wall</title><desc lang="en">Teams of two compete for life-changing amounts of cash that can be lost in an instant.</desc><category lang="en">Game Shows</category><icon src="https://cdn.tvpassport.com/image/show/480x720/61043.jpg"/></programme>
<programme start="20211120020000 +0000" stop="20211120053700 +0000" channel="WVGNLD.us"><title lang="en">Dateline NBC</title><desc lang="en">Convicted murderer Drew Peterson speaks out in the first network TV interview in over a decade. He speaks about the murder of his third wife and the disappearance of his fourth wife, Stacy Peterson. Drew&apos;s brother also speaks out for the first time.</desc><category lang="en">News Magazine</category><icon src="https://cdn.tvpassport.com/image/show/480x720/6021.jpg"/></programme>
<programme start="20211120053700 +0000" stop="20211120063700 +0000" channel="WVGNLD.us"><title lang="en">Late Night With Seth Meyers</title><desc lang="en">Guests include Sarah Silverman, Gary Gulman and Mark Ronson. Elmo Lovano sits-in with the 8G Band.</desc><category lang="en">Talk Shows</category></programme>
<programme start="20211120063700 +0000" stop="20211120070000 +0000" channel="WVGNLD.us"><title lang="en">NBC Nightly News With Lester Holt</title><desc lang="en">This daily evening news program features the top national and international stories of the day.</desc><category lang="en">News</category><icon src="https://cdn.tvpassport.com/image/show/480x720/60238.jpg"/></programme>
<programme start="20211120070000 +0000" stop="20211120080000 +0000" channel="WVGNLD.us"><title lang="en">Today</title><desc lang="en">Features the latest in international news and weather, including newsmaker interviews.</desc><category lang="en">Talk Shows</category><icon src="https://cdn.tvpassport.com/image/show/480x720/33364.jpg"/></programme>
<programme start="20211120080000 +0000" stop="20211120083000 +0000" channel="WVGNLD.us"><title lang="en">1st Look</title><desc lang="en">Your guide to the county&apos;s best food, nightlife, travel and more.</desc><category lang="en">News Magazine</category><icon src="https://cdn.tvpassport.com/image/show/480x720/37511.jpg"/></programme>
<programme start="20211120083000 +0000" stop="20211120090000 +0000" channel="WVGNLD.us"><title lang="en">1st Look</title><desc lang="en">Your guide to the county&apos;s best food, nightlife, travel and more.</desc><category lang="en">News Magazine</category><icon src="https://cdn.tvpassport.com/image/show/480x720/37511.jpg"/></programme>
<programme start="20211120090000 +0000" stop="20211120093000 +0000" channel="WVGNLD.us"><title lang="en">1st Look</title><desc lang="en">Your guide to the county&apos;s best food, nightlife, travel and more.</desc><category lang="en">News Magazine</category><icon src="https://cdn.tvpassport.com/image/show/480x720/37511.jpg"/></programme>
<programme start="20211120093000 +0000" stop="20211120100000 +0000" channel="WVGNLD.us"><title lang="en">Paid Program</title><desc lang="en">Paid programming.</desc><category lang="en">Paid Program</category></programme>
<programme start="20211120100000 +0000" stop="20211120103000 +0000" channel="WVGNLD.us"><title lang="en">Paid Program</title><desc lang="en">Paid programming.</desc><category lang="en">Paid Program</category></programme>
<programme start="20211120103000 +0000" stop="20211120110000 +0000" channel="WVGNLD.us"><title lang="en">Wild About Animals</title><desc lang="en">This week we head to the tropical paradise of Hawaii. Things start off on the rooftop of a popular Maui resort that has created a home for 300,000 bees.</desc><category lang="en">Animals</category><icon src="https://cdn.tvpassport.com/image/show/480x720/51569.jpg"/></programme>
<programme start="20211120110000 +0000" stop="20211120113000 +0000" channel="WVGNLD.us"><title lang="en">Today&apos;s Homeowner With Danny Lipford</title><desc lang="en">Chelsea moves to a larger home with new projects to tackle.</desc><category lang="en">Home</category><icon src="https://cdn.tvpassport.com/image/show/480x720/59684.jpg"/></programme>
<programme start="20211120113000 +0000" stop="20211120120000 +0000" channel="WVGNLD.us"><title lang="en">George to the Rescue</title><desc lang="en">George Oliphant comes to the rescue of families in need by renovating their homes.</desc><category lang="en">Home</category></programme>
<programme start="20211120120000 +0000" stop="20211120133000 +0000" channel="WVGNLD.us"><title lang="en">Saturday Today</title><desc lang="en">This weekend morning show covers breaking news and a variety of feature stories.</desc><category lang="en">Talk Shows</category></programme>
<programme start="20211120133000 +0000" stop="20211120140000 +0000" channel="WVGNLD.us"><title lang="en">Dog Tales</title><desc lang="en">A facility designed for agility training is visited; advice for finding a properly suited trainer is shown; the pug breed is profiled.</desc><category lang="en">Animals</category><icon src="https://cdn.tvpassport.com/image/show/480x720/59576.jpg"/></programme>
<programme start="20211120140000 +0000" stop="20211120143000 +0000" channel="WVGNLD.us"><title lang="en">Paid Program</title><desc lang="en">Paid programming.</desc><category lang="en">Paid Program</category></programme>
<programme start="20211120143000 +0000" stop="20211120150000 +0000" channel="WVGNLD.us"><title lang="en">Paid Program</title><desc lang="en">Paid programming.</desc><category lang="en">Paid Program</category></programme>
<programme start="20211120150000 +0000" stop="20211120153000 +0000" channel="WVGNLD.us"><title lang="en">Earth Odyssey With Dylan Dreyer</title><desc lang="en">An incredible journey across the globe connects the environment, wildlife and humans.</desc><category lang="en">Travel</category></programme>
<programme start="20211120153000 +0000" stop="20211120160000 +0000" channel="WVGNLD.us"><title lang="en">Wild Child</title><desc lang="en">Adventure to meet the cutest, most curious, most fascinating baby animals on the planet.</desc><category lang="en">Children</category></programme>
<programme start="20211120160000 +0000" stop="20211120163000 +0000" channel="WVGNLD.us"><title lang="en">Roots Less Traveled</title><desc lang="en">Two family members learn about their family history and each other.</desc><category lang="en">Children</category><icon src="https://cdn.tvpassport.com/image/show/480x720/104580.jpg"/></programme>
<programme start="20211120163000 +0000" stop="20211120170000 +0000" channel="WVGNLD.us"><title lang="en">One Team: The Power of Sports</title><desc lang="en">We discover the love affair between Olympians and their sport.</desc><category lang="en">Children, Miscellaneous</category></programme>
<programme start="20211120170000 +0000" stop="20211120173000 +0000" channel="WVGNLD.us"><title lang="en">Paid Program</title><desc lang="en">Paid programming.</desc><category lang="en">Paid Program</category></programme>
<programme start="20211120173000 +0000" stop="20211120193000 +0000" channel="WVGNLD.us"><title lang="en">Soccer</title><category lang="en">Sports, Soccer</category></programme>
<programme start="20211120193000 +0000" stop="20211120230000 +0000" channel="WVGNLD.us"><title lang="en">Football</title><desc lang="en">Football.</desc><category lang="en">Sports, Football</category></programme>
<programme start="20211120230000 +0000" stop="20211120233000 +0000" channel="WVGNLD.us"><title lang="en">News 4 New York Weekend Edition</title><category lang="en">News</category></programme>
<programme start="20211120233000 +0000" stop="20211121000000 +0000" channel="WVGNLD.us"><title lang="en">NBC Nightly News: Weekend Edition</title><desc lang="en">Timely reports on national and international news events that take place over the weekend.</desc><category lang="en">News</category></programme>
<programme start="20211118233000 +0000" stop="20211119013000 +0000" channel="WVXF.us"><title lang="en">Mulholland Falls</title><desc lang="en">An elite group of police detectives fight to stay alive during a murder investigation.</desc><category lang="en">Movies, Crime Story</category><icon src="https://cdn.tvpassport.com/image/show/480x720/39134.jpg"/></programme>
<programme start="20211119013000 +0000" stop="20211119040000 +0000" channel="WVXF.us"><title lang="en">Red Corner</title><desc lang="en">When a lawyer is framed for murder in China, he becomes trapped in the justice system.</desc><category lang="en">Movies, Suspense</category><icon src="https://cdn.tvpassport.com/image/show/480x720/43850.jpg"/></programme>
<programme start="20211119040000 +0000" stop="20211119060000 +0000" channel="WVXF.us"><title lang="en">Ordeal by Innocence</title><desc lang="en">A man finds that a person he gave a ride to before a trip has been executed.</desc><category lang="en">Movies, Mystery</category></programme>
<programme start="20211119060000 +0000" stop="20211119080000 +0000" channel="WVXF.us"><title lang="en">Body of Evidence</title><desc lang="en">A young woman is accused of murdering her wealthy lover for eight million dollars left to her in the will.</desc><category lang="en">Movies, Thriller</category><icon src="https://cdn.tvpassport.com/image/show/480x720/40708.jpg"/></programme>
<programme start="20211119080000 +0000" stop="20211119100000 +0000" channel="WVXF.us"><title lang="en">Fatal Charm</title><desc lang="en">A teenager begins a relationship-by-mail with a man convicted of murdering six young women.</desc><category lang="en">Movies, Thriller</category></programme>
<programme start="20211119100000 +0000" stop="20211119103000 +0000" channel="WVXF.us"><title lang="en">Paid Program</title><desc lang="en">Paid programming.</desc><category lang="en">Paid Program</category></programme>
<programme start="20211119103000 +0000" stop="20211119110000 +0000" channel="WVXF.us"><title lang="en">Paid Program</title><desc lang="en">Paid programming.</desc><category lang="en">Paid Program</category></programme>
<programme start="20211119110000 +0000" stop="20211119113000 +0000" channel="WVXF.us"><title lang="en">Paid Program</title><desc lang="en">Paid programming.</desc><category lang="en">Paid Program</category></programme>
<programme start="20211119113000 +0000" stop="20211119120000 +0000" channel="WVXF.us"><title lang="en">Paid Program</title><desc lang="en">Paid programming.</desc><category lang="en">Paid Program</category></programme>
<programme start="20211119120000 +0000" stop="20211119123000 +0000" channel="WVXF.us"><title lang="en">Paid Program</title><desc lang="en">Paid programming.</desc><category lang="en">Paid Program</category></programme>
<programme start="20211119123000 +0000" stop="20211119130000 +0000" channel="WVXF.us"><title lang="en">Paid Program</title><desc lang="en">Paid programming.</desc><category lang="en">Paid Program</category></programme>
<programme start="20211119130000 +0000" stop="20211119133000 +0000" channel="WVXF.us"><title lang="en">Paid Program</title><desc lang="en">Paid programming.</desc><category lang="en">Paid Program</category></programme>
<programme start="20211119133000 +0000" stop="20211119140000 +0000" channel="WVXF.us"><title lang="en">Paid Program</title><desc lang="en">Paid programming.</desc><category lang="en">Paid Program</category></programme>
<programme start="20211119140000 +0000" stop="20211119143000 +0000" channel="WVXF.us"><title lang="en">Get Wild at the San Diego Zoo</title><category lang="en">Children</category></programme>
<programme start="20211119143000 +0000" stop="20211119150000 +0000" channel="WVXF.us"><title lang="en">Science Nation</title><category lang="en">Science</category></programme>
<programme start="20211119150000 +0000" stop="20211119183000 +0000" channel="WVXF.us"><title lang="en">New York, New York</title><desc lang="en">A couple&apos;s rushed marriage disintegrates after two children and many arguments.</desc><category lang="en">Movies, Drama</category><icon src="https://cdn.tvpassport.com/image/show/480x720/18644.jpg"/></programme>
<programme start="20211119183000 +0000" stop="20211119203000 +0000" channel="WVXF.us"><title lang="en">Blizzard</title><desc lang="en">A young girl&apos;s aunt tells her the tale of Blizzard, an enchanted reindeer, who helps a girl pursuing her dream to become a figure skating champion.</desc><category lang="en">Movies, Christmas, Family</category><icon src="https://cdn.tvpassport.com/image/show/480x720/24149.jpg"/></programme>
<programme start="20211119203000 +0000" stop="20211119223000 +0000" channel="WVXF.us"><title lang="en">The Secret of N.I.M.H.</title><desc lang="en">A secret society of intelligent lab rats help a widowed mouse protect her home and family.</desc><category lang="en">Movies, Animated</category><icon src="https://cdn.tvpassport.com/image/show/480x720/20839.jpg"/></programme>
<programme start="20211119223000 +0000" stop="20211120010000 +0000" channel="WVXF.us"><title lang="en">The Black Stallion</title><desc lang="en">A boy&apos;s adventure with a magnificent black stallion results in a close friendship.</desc><category lang="en">Movies, Family</category><icon src="https://cdn.tvpassport.com/image/show/480x720/38627.jpg"/></programme>
<programme start="20211119223000 +0000" stop="20211120010000 +0000" channel="WVXF.us"><title lang="en">The Black Stallion</title><desc lang="en">A boy&apos;s adventure with a magnificent black stallion results in a close friendship.</desc><category lang="en">Movies, Family</category><icon src="https://cdn.tvpassport.com/image/show/480x720/38627.jpg"/></programme>
<programme start="20211120010000 +0000" stop="20211120030000 +0000" channel="WVXF.us"><title lang="en">The Black Stallion Returns</title><desc lang="en">A teen searches the Sahara desert for his beloved black stallion, which was stolen from him.</desc><category lang="en">Movies, Adventure</category><icon src="https://cdn.tvpassport.com/image/show/480x720/44816.jpg"/></programme>
<programme start="20211120030000 +0000" stop="20211120050000 +0000" channel="WVXF.us"><title lang="en">The Dust Factory</title><desc lang="en">Two teenage boys help each other through difficult times in their lives while they prepare for their next life phase.</desc><category lang="en">Movies, Drama</category><icon src="https://cdn.tvpassport.com/image/show/480x720/33916.jpg"/></programme>
<programme start="20211120050000 +0000" stop="20211120080000 +0000" channel="WVXF.us"><title lang="en">New York, New York</title><desc lang="en">A couple&apos;s rushed marriage disintegrates after two children and many arguments.</desc><category lang="en">Movies, Drama</category><icon src="https://cdn.tvpassport.com/image/show/480x720/18644.jpg"/></programme>
<programme start="20211120080000 +0000" stop="20211120083000 +0000" channel="WVXF.us"><title lang="en">To Be Announced</title><desc lang="en">Movie</desc><category lang="en">Movies</category></programme>
<programme start="20211120083000 +0000" stop="20211120090000 +0000" channel="WVXF.us"><title lang="en">The Rat Patrol</title><desc lang="en">The adventures of an elite team of commandos stationed in North Africa during the war.</desc><category lang="en">Drama</category></programme>
<programme start="20211120090000 +0000" stop="20211120100000 +0000" channel="WVXF.us"><title lang="en">Poltergeist: The Legacy</title><desc lang="en">A grieving woman seeks revenge for her granddaughter&apos;s murder and curses a family.</desc><category lang="en">Drama</category></programme>
<programme start="20211120100000 +0000" stop="20211120103000 +0000" channel="WVXF.us"><title lang="en">Paid Program</title><desc lang="en">Paid programming.</desc><category lang="en">Paid Program</category></programme>
<programme start="20211120103000 +0000" stop="20211120110000 +0000" channel="WVXF.us"><title lang="en">Paid Program</title><desc lang="en">Paid programming.</desc><category lang="en">Paid Program</category></programme>
<programme start="20211120110000 +0000" stop="20211120113000 +0000" channel="WVXF.us"><title lang="en">Paid Program</title><desc lang="en">Paid programming.</desc><category lang="en">Paid Program</category></programme>
<programme start="20211120113000 +0000" stop="20211120120000 +0000" channel="WVXF.us"><title lang="en">Paid Program</title><desc lang="en">Paid programming.</desc><category lang="en">Paid Program</category></programme>
<programme start="20211120120000 +0000" stop="20211120123000 +0000" channel="WVXF.us"><title lang="en">Paid Program</title><desc lang="en">Paid programming.</desc><category lang="en">Paid Program</category></programme>
<programme start="20211120123000 +0000" stop="20211120130000 +0000" channel="WVXF.us"><title lang="en">Paid Program</title><desc lang="en">Paid programming.</desc><category lang="en">Paid Program</category></programme>
<programme start="20211120130000 +0000" stop="20211120133000 +0000" channel="WVXF.us"><title lang="en">Paid Program</title><desc lang="en">Paid programming.</desc><category lang="en">Paid Program</category></programme>
<programme start="20211120133000 +0000" stop="20211120140000 +0000" channel="WVXF.us"><title lang="en">Paid Program</title><desc lang="en">Paid programming.</desc><category lang="en">Paid Program</category></programme>
<programme start="20211120140000 +0000" stop="20211120143000 +0000" channel="WVXF.us"><title lang="en">The Rat Patrol</title><desc lang="en">The adventures of an elite team of commandos stationed in North Africa during the war.</desc><category lang="en">Drama</category></programme>
<programme start="20211120143000 +0000" stop="20211120150000 +0000" channel="WVXF.us"><title lang="en">The Rat Patrol</title><desc lang="en">The adventures of an elite team of commandos stationed in North Africa during the war.</desc><category lang="en">Drama</category></programme>
<programme start="20211120150000 +0000" stop="20211120173000 +0000" channel="WVXF.us"><title lang="en">Barquero</title><desc lang="en">A bandit demands that a ferryman transport his gang and their booty across the river.</desc><category lang="en">Movies, Western</category></programme>
<programme start="20211120173000 +0000" stop="20211120200000 +0000" channel="WVXF.us"><title lang="en">Billy Two Hats</title><desc lang="en">Two fugitives try to stay ahead of the obstacles that threaten their lives and freedom.</desc><category lang="en">Movies, Western</category><icon src="https://cdn.tvpassport.com/image/show/480x720/46486.jpg"/></programme>
<programme start="20211120200000 +0000" stop="20211120220000 +0000" channel="WVXF.us"><title lang="en">Breakheart Pass</title><desc lang="en">Posing as a fugitive from justice, an undercover agent in the American frontier during the 1870s boards a train to unravel a conspiracy that&apos;s underway at a military outpost.</desc><category lang="en">Movies, Action</category><icon src="https://cdn.tvpassport.com/image/show/480x720/19220.jpg"/></programme>
<programme start="20211120220000 +0000" stop="20211121000000 +0000" channel="WVXF.us"><title lang="en">Cattle Annie and Little Britches</title><desc lang="en">Two teenage girls rally what&apos;s left of the Doolin-Dalton outlaw gang after Doolin is caught.</desc><category lang="en">Movies, Western</category></programme>
</tv>